Workbook

Sheet Raw Data
A1: Invoice ID | B1: Invoice Date | C1: Due Date | D1: Vendor ID | E1: Vendor Name | F1: Expense Category | G1: Department | H1: Description | I1: Quantity | J1: Unit Cost | K1: Invoice Amount | L1: Payment Status | M1: Payment Date | N1: Payment Method
A2: INV-0001 | B2: 2025-01-13 | C2: 2025-02-27 | D2: V002 | E2: Tech Solutions Ltd | F2: Software | G2: IT | H2: Business application | I2: 4 | J2: 885.59 | K2: 3542.36 | L2: Paid | M2: 2025-01-21 | N2: UPI
A3: INV-0002 | B3: 2025-01-16 | C3: 2025-01-31 | D3: V001 | E3: ABC Office Supplies | F3: Office Supplies | G3: Administration | H3: Printer paper | I3: 18 | J3: 428 | K3: 7703.99 | L3: Paid | M3: 2025-01-31 | N3: UPI
A4: INV-0003 | B4: 2025-08-18 | C4: 2025-10-02 | D4: V004 | E4: Bright Marketing Co | F4: Marketing | G4: Marketing | H4: Digital advertising | I4: 14 | J4: 933.73 | K4: 13072.18 | L4: Paid | M4: 2025-09-11 | N4: Cheque
A5: INV-0004 | B5: 2025-04-21 | C5: 2025-05-21 | D5: V003 | E5: CleanPro Services | F5: Facilities | G5: Facilities | H5: Maintenance | I5: 12 | J5: 487.83 | K5: 5853.93 | L5: Paid | M5: 2025-05-10 | N5: Bank Transfer
A6: INV-0005 | B6: 2025-10-02 | C6: 2025-10-17 | D6: V008 | E6: CloudWorks Software | F6: Software | G6: IT | H6: Business application | I6: 10 | J6: 583.34 | K6: 5833.38 | L6: Overdue
A7: INV-0006 | B7: 2025-07-05 | C7: 2025-08-19 | D7: V010 | E7: FreshBite Catering | F7: Office Supplies | G7: Administration | H7: Printer cartridges | I7: 8 | J7: 159.49 | K7: 1275.94 | L7: Paid | M7: 2025-07-26 | N7: Bank Transfer
A8: INV-0007 | B8: 2025-02-21 | C8: 2025-03-23 | D8: V004 | E8: Bright Marketing Co | F8: Marketing | G8: Marketing | H8: Printing and promotion | I8: 6 | J8: 1604.39 | K8: 9626.35 | L8: Paid | M8: 2025-03-19 | N8: Cheque
A9: INV-0008 | B9: 2025-12-10 | C9: 2026-01-09 | D9: V004 | E9: Bright Marketing Co | F9: Marketing | G9: Marketing | H9: Digital advertising | I9: 20 | J9: 516.62 | K9: 10332.33 | L9: Pending
A10: INV-0009 | B10: 2025-10-01 | C10: 2025-11-15 | D10: V003 | E10: CleanPro Services | F10: Facilities | G10: Facilities | H10: Maintenance | I10: 18 | J10: 392.69 | K10: 7068.34 | L10: Paid | M10: 2025-10-18 | N10: Cheque
A11: INV-0010 | B11: 2025-04-28 | C11: 2025-05-13 | D11: V001 | E11: ABC Office Supplies | F11: Office Supplies | G11: Administration | H11: Printer paper | I11: 7 | J11: 881.03 | K11: 6167.18 | L11: Pending
A12: INV-0011 | B12: 2025-06-11 | C12: 2025-06-26 | D12: V010 | E12: FreshBite Catering | F12: Office Supplies | G12: Administration | H12: Printer cartridges | I12: 15 | J12: 405.7 | K12: 6085.57 | L12: Pending
A13: INV-0012 | B13: 2025-05-16 | C13: 2025-05-31 | D13: V003 | E13: CleanPro Services | F13: Facilities | G13: Facilities | H13: Maintenance | I13: 19 | J13: 448.96 | K13: 8530.18 | L13: Paid | M13: 2025-06-15 | N13: UPI
A14: INV-0013 | B14: 2025-04-23 | C14: 2025-05-08 | D14: V006 | E14: PeopleFirst HR Services | F14: HR Services | G14: HR | H14: Recruitment service | I14: 4 | J14: 397.73 | K14: 1590.91 | L14: Paid | M14: 2025-05-05 | N14: Credit Card
A15: INV-0014 | B15: 2025-11-02 | C15: 2025-11-17 | D15: V007 | E15: SafeGuard Security | F15: Facilities | G15: Facilities | H15: Maintenance | I15: 17 | J15: 531.73 | K15: 9039.35 | L15: Paid | M15: 2025-11-21 | N15: Bank Transfer
A16: INV-0015 | B16: 2025-12-16 | C16: 2026-01-30 | D16: V002 | E16: Tech Solutions Ltd | F16: Software | G16: IT | H16: Cloud storage | I16: 4 | J16: 2896.71 | K16: 11586.83 | L16: Pending
A17: INV-0016 | B17: 2025-08-11 | C17: 2025-08-26 | D17: V005 | E17: Metro Logistics | F17: Logistics | G17: Operations | H17: Delivery service | I17: 9 | J17: 1590.98 | K17: 14318.78 | L17: Paid | M17: 2025-09-15 | N17: Credit Card
A18: INV-0017 | B18: 2025-02-24 | C18: 2025-04-10 | D18: V009 | E18: Prime Travel Services | F18: Travel | G18: Operations | H18: Travel expenses | I18: 7 | J18: 1382.07 | K18: 9674.51 | L18: Paid | M18: 2025-03-08 | N18: Cheque
A19: INV-0018 | B19: 2025-10-04 | C19: 2025-11-18 | D19: V003 | E19: CleanPro Services | F19: Facilities | G19: Facilities | H19: Maintenance | I19: 1 | J19: 9084.43 | K19: 9084.43 | L19: Overdue
A20: INV-0019 | B20: 2025-07-05 | C20: 2025-08-04 | D20: V002 | E20: Tech Solutions Ltd | F20: Software | G20: IT | H20: Business application | I20: 3 | J20: 1267.62 | K20: 3802.86 | L20: Paid | M20: 2025-07-13 | N20: UPI
A21: INV-0020 | B21: 2025-09-30 | C21: 2025-10-15 | D21: V002 | E21: Tech Solutions Ltd | F21: Software | G21: IT | H21: Business application | I21: 6 | J21: 1210.07 | K21: 7260.42 | L21: Paid | M21: 2025-10-19 | N21: UPI
A22: INV-0021 | B22: 2025-10-04 | C22: 2025-11-18 | D22: V004 | E22: Bright Marketing Co | F22: Marketing | G22: Marketing | H22: Printing and promotion | I22: 12 | J22: 897.17 | K22: 10766 | L22: Pending
A23: INV-0022 | B23: 2025-09-22 | C23: 2025-10-22 | D23: V008 | E23: CloudWorks Software | F23: Software | G23: IT | H23: Cloud storage | I23: 1 | J23: 3564.29 | K23: 3564.29 | L23: Paid | M23: 2025-10-09 | N23: Credit Card
A24: INV-0023 | B24: 2025-02-06 | C24: 2025-03-23 | D24: V001 | E24: ABC Office Supplies | F24: Office Supplies | G24: Administration | H24: Printer paper | I24: 11 | J24: 329.72 | K24: 3626.89 | L24: Pending
A25: INV-0024 | B25: 2025-09-21 | C25: 2025-10-06 | D25: V002 | E25: Tech Solutions Ltd | F25: Software | G25: IT | H25: Business application | I25: 5 | J25: 1481.97 | K25: 7409.86 | L25: Paid | M25: 2025-10-24 | N25: Credit Card
A26: INV-0025 | B26: 2025-07-28 | C26: 2025-08-12 | D26: V008 | E26: CloudWorks Software | F26: Software | G26: IT | H26: Cloud storage | I26: 14 | J26: 712.14 | K26: 9970 | L26: Paid | M26: 2025-08-26 | N26: UPI
A27: INV-0026 | B27: 2025-12-11 | C27: 2026-01-25 | D27: V001 | E27: ABC Office Supplies | F27: Office Supplies | G27: Administration | H27: Pens and stationery | I27: 11 | J27: 154.7 | K27: 1701.66 | L27: Overdue
A28: INV-0027 | B28: 2025-05-08 | C28: 2025-05-23 | D28: V002 | E28: Tech Solutions Ltd | F28: Software | G28: IT | H28: Cloud storage | I28: 6 | J28: 1144.51 | K28: 6867.05 | L28: Paid | M28: 2025-05-28 | N28: UPI
A29: INV-0028 | B29: 2025-02-08 | C29: 2025-03-10 | D29: V004 | E29: Bright Marketing Co | F29: Marketing | G29: Marketing | H29: Digital advertising | I29: 2 | J29: 6437.76 | K29: 12875.51 | L29: Pending
A30: INV-0029 | B30: 2025-01-08 | C30: 2025-01-23 | D30: V009 | E30: Prime Travel Services | F30: Travel | G30: Operations | H30: Flight booking | I30: 14 | J30: 912.02 | K30: 12768.26 | L30: Overdue
A31: INV-0030 | B31: 2025-09-04 | C31: 2025-09-19 | D31: V008 | E31: CloudWorks Software | F31: Software | G31: IT | H31: Software subscription | I31: 13 | J31: 1043.16 | K31: 13561.03 | L31: Overdue
A32: INV-0031 | B32: 2025-07-19 | C32: 2025-08-18 | D32: V001 | E32: ABC Office Supplies | F32: Office Supplies | G32: Administration | H32: Pens and stationery | I32: 14 | J32: 845.05 | K32: 11830.66 | L32: Overdue
A33: INV-0032 | B33: 2025-12-05 | C33: 2026-01-19 | D33: V009 | E33: Prime Travel Services | F33: Travel | G33: Operations | H33: Flight booking | I33: 2 | J33: 1525.49 | K33: 3050.99 | L33: Paid | M33: 2025-12-11 | N33: Cheque
A34: INV-0033 | B34: 2025-01-26 | C34: 2025-03-12 | D34: V001 | E34: ABC Office Supplies | F34: Office Supplies | G34: Administration | H34: Printer cartridges | I34: 6 | J34: 2301.83 | K34: 13810.96 | L34: Paid | M34: 2025-02-01 | N34: Bank Transfer
A35: INV-0034 | B35: 2025-02-05 | C35: 2025-03-22 | D35: V003 | E35: CleanPro Services | F35: Facilities | G35: Facilities | H35: Maintenance | I35: 4 | J35: 3240.46 | K35: 12961.83 | L35: Paid | M35: 2025-02-23 | N35: Bank Transfer
A36: INV-0035 | B36: 2025-02-11 | C36: 2025-03-13 | D36: V010 | E36: FreshBite Catering | F36: Office Supplies | G36: Administration | H36: Pens and stationery | I36: 9 | J36: 954.12 | K36: 8587.1 | L36: Pending
A37: INV-0036 | B37: 2025-12-09 | C37: 2026-01-23 | D37: V004 | E37: Bright Marketing Co | F37: Marketing | G37: Marketing | H37: Digital advertising | I37: 10 | J37: 416.78 | K37: 4167.81 | L37: Paid | M37: 2026-01-10 | N37: Cheque
A38: INV-0037 | B38: 2025-01-05 | C38: 2025-02-04 | D38: V002 | E38: Tech Solutions Ltd | F38: Software | G38: IT | H38: Software subscription | I38: 3 | J38: 2851.39 | K38: 8554.16 | L38: Pending
A39: INV-0038 | B39: 2025-04-20 | C39: 2025-06-04 | D39: V009 | E39: Prime Travel Services | F39: Travel | G39: Operations | H39: Flight booking | I39: 8 | J39: 1751.95 | K39: 14015.58 | L39: Paid | M39: 2025-05-16 | N39: Cheque
A40: INV-0039 | B40: 2025-08-13 | C40: 2025-09-27 | D40: V003 | E40: CleanPro Services | F40: Facilities | G40: Facilities | H40: Security service | I40: 17 | J40: 545.43 | K40: 9272.25 | L40: Pending
A41: INV-0040 | B41: 2025-12-08 | C41: 2026-01-22 | D41: V001 | E41: ABC Office Supplies | F41: Office Supplies | G41: Administration | H41: Printer paper | I41: 9 | J41: 1115 | K41: 10034.98 | L41: Paid | M41: 2025-12-18 | N41: Bank Transfer
A42: INV-0041 | B42: 2025-03-21 | C42: 2025-04-20 | D42: V009 | E42: Prime Travel Services | F42: Travel | G42: Operations | H42: Hotel accommodation | I42: 7 | J42: 479.54 | K42: 3356.79 | L42: Paid | M42: 2025-04-09 | N42: UPI
A43: INV-0042 | B43: 2025-01-27 | C43: 2025-02-11 | D43: V005 | E43: Metro Logistics | F43: Logistics | G43: Operations | H43: Courier service | I43: 1 | J43: 12482.88 | K43: 12482.88 | L43: Pending
A44: INV-0043 | B44: 2025-03-08 | C44: 2025-04-22 | D44: V006 | E44: PeopleFirst HR Services | F44: HR Services | G44: HR | H44: Training service | I44: 18 | J44: 146.3 | K44: 2633.33 | L44: Overdue
A45: INV-0044 | B45: 2025-10-15 | C45: 2025-10-30 | D45: V007 | E45: SafeGuard Security | F45: Facilities | G45: Facilities | H45: Security service | I45: 5 | J45: 2837.9 | K45: 14189.5 | L45: Paid | M45: 2025-10-20 | N45: Cheque
A46: INV-0045 | B46: 2025-10-10 | C46: 2025-10-25 | D46: V010 | E46: FreshBite Catering | F46: Office Supplies | G46: Administration | H46: Pens and stationery | I46: 2 | J46: 433.49 | K46: 866.98 | L46: Paid | M46: 2025-11-04 | N46: Credit Card
A47: INV-0046 | B47: 2025-12-08 | C47: 2025-12-23 | D47: V004 | E47: Bright Marketing Co | F47: Marketing | G47: Marketing | H47: Printing and promotion | I47: 20 | J47: 425.41 | K47: 8508.28 | L47: Paid | M47: 2025-12-20 | N47: Credit Card
A48: INV-0047 | B48: 2025-04-01 | C48: 2025-05-01 | D48: V003 | E48: CleanPro Services | F48: Facilities | G48: Facilities | H48: Maintenance | I48: 14 | J48: 793.88 | K48: 11114.33 | L48: Paid | M48: 2025-04-19 | N48: Cheque
A49: INV-0048 | B49: 2025-12-26 | C49: 2026-01-10 | D49: V003 | E49: CleanPro Services | F49: Facilities | G49: Facilities | H49: Maintenance | I49: 8 | J49: 102.65 | K49: 821.19 | L49: Paid | M49: 2026-01-10 | N49: UPI
A50: INV-0049 | B50: 2025-06-06 | C50: 2025-06-21 | D50: V006 | E50: PeopleFirst HR Services | F50: HR Services | G50: HR | H50: Training service | I50: 11 | J50: 907.77 | K50: 9985.49 | L50: Paid | M50: 2025-06-26 | N50: Bank Transfer
A51: INV-0050 | B51: 2025-06-29 | C51: 2025-08-13 | D51: V005 | E51: Metro Logistics | F51: Logistics | G51: Operations | H51: Delivery service | I51: 11 | J51: 933.9 | K51: 10272.89 | L51: Paid | M51: 2025-07-03 | N51: Bank Transfer
A52: INV-0051 | B52: 2025-04-02 | C52: 2025-05-17 | D52: V005 | E52: Metro Logistics | F52: Logistics | G52: Operations | H52: Courier service | I52: 20 | J52: 208.28 | K52: 4165.63 | L52: Overdue
A53: INV-0052 | B53: 2025-06-26 | C53: 2025-08-10 | D53: V007 | E53: SafeGuard Security | F53: Facilities | G53: Facilities | H53: Security service | I53: 4 | J53: 1671.7 | K53: 6686.81 | L53: Pending
A54: INV-0053 | B54: 2025-10-23 | C54: 2025-11-07 | D54: V007 | E54: SafeGuard Security | F54: Facilities | G54: Facilities | H54: Cleaning service | I54: 17 | J54: 629.68 | K54: 10704.58 | L54: Paid | M54: 2025-11-07 | N54: Cheque
A55: INV-0054 | B55: 2025-02-05 | C55: 2025-03-22 | D55: V007 | E55: SafeGuard Security | F55: Facilities | G55: Facilities | H55: Security service | I55: 4 | J55: 2360.39 | K55: 9441.54 | L55: Overdue
A56: INV-0055 | B56: 2025-09-17 | C56: 2025-10-17 | D56: V005 | E56: Metro Logistics | F56: Logistics | G56: Operations | H56: Delivery service | I56: 10 | J56: 506.12 | K56: 5061.2 | L56: Pending
A57: INV-0056 | B57: 2025-03-07 | C57: 2025-03-22 | D57: V009 | E57: Prime Travel Services | F57: Travel | G57: Operations | H57: Travel expenses | I57: 6 | J57: 2353.39 | K57: 14120.36 | L57: Paid | M57: 2025-03-29 | N57: UPI
A58: INV-0057 | B58: 2025-01-01 | C58: 2025-01-31 | D58: V009 | E58: Prime Travel Services | F58: Travel | G58: Operations | H58: Travel expenses | I58: 20 | J58: 329.54 | K58: 6590.85 | L58: Paid | M58: 2025-01-24 | N58: UPI
A59: INV-0058 | B59: 2025-08-15 | C59: 2025-09-29 | D59: V008 | E59: CloudWorks Software | F59: Software | G59: IT | H59: Business application | I59: 6 | J59: 1204.92 | K59: 7229.5 | L59: Paid | M59: 2025-08-23 | N59: Cheque
A60: INV-0059 | B60: 2025-12-06 | C60: 2026-01-20 | D60: V009 | E60: Prime Travel Services | F60: Travel | G60: Operations | H60: Flight booking | I60: 10 | J60: 162.75 | K60: 1627.46 | L60: Pending
A61: INV-0060 | B61: 2025-04-12 | C61: 2025-04-27 | D61: V004 | E61: Bright Marketing Co | F61: Marketing | G61: Marketing | H61: Printing and promotion | I61: 20 | J61: 193.07 | K61: 3861.43 | L61: Paid | M61: 2025-04-19 | N61: UPI
A62: INV-0061 | B62: 2025-11-19 | C62: 2026-01-03 | D62: V007 | E62: SafeGuard Security | F62: Facilities | G62: Facilities | H62: Maintenance | I62: 13 | J62: 809.33 | K62: 10521.23 | L62: Paid | M62: 2025-12-07 | N62: Credit Card
A63: INV-0062 | B63: 2025-02-24 | C63: 2025-03-26 | D63: V001 | E63: ABC Office Supplies | F63: Office Supplies | G63: Administration | H63: Printer cartridges | I63: 17 | J63: 712.39 | K63: 12110.62 | L63: Paid | M63: 2025-03-28 | N63: Bank Transfer
A64: INV-0063 | B64: 2025-05-08 | C64: 2025-05-23 | D64: V009 | E64: Prime Travel Services | F64: Travel | G64: Operations | H64: Travel expenses | I64: 17 | J64: 710.05 | K64: 12070.89 | L64: Paid | M64: 2025-05-31 | N64: UPI
A65: INV-0064 | B65: 2025-09-16 | C65: 2025-10-16 | D65: V010 | E65: FreshBite Catering | F65: Office Supplies | G65: Administration | H65: Printer paper | I65: 16 | J65: 520.69 | K65: 8331.11 | L65: Pending
A66: INV-0065 | B66: 2025-05-13 | C66: 2025-05-28 | D66: V008 | E66: CloudWorks Software | F66: Software | G66: IT | H66: Business application | I66: 16 | J66: 271.27 | K66: 4340.34 | L66: Pending
A67: INV-0066 | B67: 2025-05-21 | C67: 2025-06-20 | D67: V004 | E67: Bright Marketing Co | F67: Marketing | G67: Marketing | H67: Printing and promotion | I67: 11 | J67: 405.86 | K67: 4464.49 | L67: Paid | M67: 2025-06-13 | N67: Bank Transfer
A68: INV-0067 | B68: 2025-03-19 | C68: 2025-04-03 | D68: V003 | E68: CleanPro Services | F68: Facilities | G68: Facilities | H68: Cleaning service | I68: 3 | J68: 834.63 | K68: 2503.88 | L68: Paid | M68: 2025-04-17 | N68: UPI
A69: INV-0068 | B69: 2025-10-05 | C69: 2025-11-04 | D69: V006 | E69: PeopleFirst HR Services | F69: HR Services | G69: HR | H69: Training service | I69: 13 | J69: 253.91 | K69: 3300.81 | L69: Paid | M69: 2025-10-09 | N69: UPI
A70: INV-0069 | B70: 2025-01-04 | C70: 2025-02-03 | D70: V008 | E70: CloudWorks Software | F70: Software | G70: IT | H70: Cloud storage | I70: 18 | J70: 333.46 | K70: 6002.3 | L70: Paid | M70: 2025-01-21 | N70: UPI
A71: INV-0070 | B71: 2025-05-20 | C71: 2025-06-19 | D71: V004 | E71: Bright Marketing Co | F71: Marketing | G71: Marketing | H71: Marketing services | I71: 13 | J71: 460.43 | K71: 5985.64 | L71: Paid | M71: 2025-06-02 | N71: UPI
A72: INV-0071 | B72: 2025-11-15 | C72: 2025-12-30 | D72: V003 | E72: CleanPro Services | F72: Facilities | G72: Facilities | H72: Security service | I72: 1 | J72: 6061.8 | K72: 6061.8 | L72: Paid | M72: 2025-11-23 | N72: UPI
A73: INV-0072 | B73: 2025-08-25 | C73: 2025-09-09 | D73: V003 | E73: CleanPro Services | F73: Facilities | G73: Facilities | H73: Cleaning service | I73: 15 | J73: 389.45 | K73: 5841.78 | L73: Paid | M73: 2025-09-17 | N73: Cheque
A74: INV-0073 | B74: 2025-05-23 | C74: 2025-06-22 | D74: V007 | E74: SafeGuard Security | F74: Facilities | G74: Facilities | H74: Cleaning service | I74: 18 | J74: 81.01 | K74: 1458.12 | L74: Paid | M74: 2025-05-29 | N74: Cheque
A75: INV-0074 | B75: 2025-11-29 | C75: 2025-12-14 | D75: V004 | E75: Bright Marketing Co | F75: Marketing | G75: Marketing | H75: Digital advertising | I75: 8 | J75: 1232.92 | K75: 9863.38 | L75: Pending
A76: INV-0075 | B76: 2025-01-11 | C76: 2025-02-25 | D76: V004 | E76: Bright Marketing Co | F76: Marketing | G76: Marketing | H76: Marketing services | I76: 4 | J76: 527.94 | K76: 2111.76 | L76: Paid | M76: 2025-01-27 | N76: UPI
A77: INV-0076 | B77: 2025-07-08 | C77: 2025-07-23 | D77: V005 | E77: Metro Logistics | F77: Logistics | G77: Operations | H77: Delivery service | I77: 4 | J77: 3616.27 | K77: 14465.09 | L77: Pending
A78: INV-0077 | B78: 2025-06-09 | C78: 2025-06-24 | D78: V003 | E78: CleanPro Services | F78: Facilities | G78: Facilities | H78: Security service | I78: 13 | J78: 1073.16 | K78: 13951.09 | L78: Paid | M78: 2025-07-07 | N78: Credit Card
A79: INV-0078 | B79: 2025-10-31 | C79: 2025-12-15 | D79: V002 | E79: Tech Solutions Ltd | F79: Software | G79: IT | H79: Business application | I79: 10 | J79: 383.2 | K79: 3832.03 | L79: Pending
A80: INV-0079 | B80: 2025-03-03 | C80: 2025-04-17 | D80: V010 | E80: FreshBite Catering | F80: Office Supplies | G80: Administration | H80: Pens and stationery | I80: 12 | J80: 447.61 | K80: 5371.26 | L80: Pending
A81: INV-0080 | B81: 2025-09-17 | C81: 2025-11-01 | D81: V002 | E81: Tech Solutions Ltd | F81: Software | G81: IT | H81: Cloud storage | I81: 4 | J81: 3195.31 | K81: 12781.24 | L81: Paid | M81: 2025-10-17 | N81: Cheque
A82: INV-0008-DUP | B82: 2025-12-10 | C82: 2026-01-09 | D82: V004 | E82: Bright Marketing Co | F82: Marketing | G82: Marketing | H82: Digital advertising | I82: 20 | J82: 516.62 | K82: 10332.33 | L82: Pending
A83: INV-0024-DUP | B83: 2025-09-21 | C83: 2025-10-06 | D83: V002 | E83: Tech Solutions Ltd | F83: Software | G83: IT | H83: Business application | I83: 5 | J83: 1481.97 | K83: 7409.86 | L83: Paid | M83: 2025-10-24 | N83: Credit Card
A84: INV-0052-DUP | B84: 2025-06-26 | C84: 2025-08-10 | D84: V007 | E84: SafeGuard Security | F84: Facilities | G84: Facilities | H84: Security service | I84: 4 | J84: 1671.7 | K84: 6686.81 | L84: Pending

Sheet Vendor Mapping
A1: Vendor ID | B1: Vendor Name | C1: Department | D1: Vendor Category
A2: V001 | B2: ABC Office Supplies | C2: Administration | D2: Office Supplies
A3: V002 | B3: Tech Solutions Ltd | C3: IT | D3: Software
A4: V003 | B4: CleanPro Services | C4: Facilities | D4: Facilities
A5: V004 | B5: Bright Marketing Co | C5: Marketing | D5: Marketing
A6: V005 | B6: Metro Logistics | C6: Operations | D6: Logistics
A7: V006 | B7: PeopleFirst HR Services | C7: HR | D7: HR Services
A8: V007 | B8: SafeGuard Security | C8: Facilities | D8: Facilities
A9: V008 | B9: CloudWorks Software | C9: IT | D9: Software
A10: V009 | B10: Prime Travel Services | C10: Operations | D10: Travel
A11: V010 | B11: FreshBite Catering | C11: Administration | D11: Office Supplies

Sheet Project Notes
A1: Project | B1: Purpose | C1: Note
A2: Invoice & Expense Analysis Dashboard | B2: Practice data cleaning, XLOOKUP, SUMIFS/COUNTIFS, PivotTables, duplicate detection, vendor/payment analysis, dashboard creation and business insights. | C2: Raw Data contains 83 records including 3 deliberate duplicate invoice records for the duplicate-identification exercise.

Sheet Cleaned Data
A1: Invoice ID | B1: Invoice Date | C1: Due Date | D1: Vendor ID | E1: Vendor Name | F1: Expense Category | G1: Department | H1: Description | I1: Quantity | J1: Unit Cost | K1: Invoice Amount | L1: Payment Status | M1: Payment Date | N1: Payment Method | O1: Lookup Department | P1: Duplicate Check | Q1: Invoice Month
A2: INV-0001 | B2: 2025-01-13 | C2: 2025-02-27 | D2: V002 | E2: Tech Solutions Ltd | F2: Software | G2: IT | H2: Business application | I2: 4 | J2: 885.59 | K2: 3542.36 | L2: Paid | M2: 2025-01-21 | N2: UPI | O2: =XLOOKUP(D2,'Vendor Mapping'!$A:$A,'Vendor Mapping'!$C:$C,"Not Found") | P2: =IF(COUNTIFS($D:$D,D2,$B:$B,B2,$K:$K,K2)>1,"Duplicate","Unique") | Q2: =TEXT(B2,"mmm")
A3: INV-0002 | B3: 2025-01-16 | C3: 2025-01-31 | D3: V001 | E3: ABC Office Supplies | F3: Office Supplies | G3: Administration | H3: Printer paper | I3: 18 | J3: 428 | K3: 7703.99 | L3: Paid | M3: 2025-01-31 | N3: UPI | O3: =XLOOKUP(D3,'Vendor Mapping'!$A:$A,'Vendor Mapping'!$C:$C,"Not Found") | P3: =IF(COUNTIFS($D:$D,D3,$B:$B,B3,$K:$K,K3)>1,"Duplicate","Unique") | Q3: =TEXT(B3,"mmm")
A4: INV-0003 | B4: 2025-08-18 | C4: 2025-10-02 | D4: V004 | E4: Bright Marketing Co | F4: Marketing | G4: Marketing | H4: Digital advertising | I4: 14 | J4: 933.73 | K4: 13072.18 | L4: Paid | M4: 2025-09-11 | N4: Cheque | O4: =XLOOKUP(D4,'Vendor Mapping'!$A:$A,'Vendor Mapping'!$C:$C,"Not Found") | P4: =IF(COUNTIFS($D:$D,D4,$B:$B,B4,$K:$K,K4)>1,"Duplicate","Unique") | Q4: =TEXT(B4,"mmm")
A5: INV-0004 | B5: 2025-04-21 | C5: 2025-05-21 | D5: V003 | E5: CleanPro Services | F5: Facilities | G5: Facilities | H5: Maintenance | I5: 12 | J5: 487.83 | K5: 5853.93 | L5: Paid | M5: 2025-05-10 | N5: Bank Transfer | O5: =XLOOKUP(D5,'Vendor Mapping'!$A:$A,'Vendor Mapping'!$C:$C,"Not Found") | P5: =IF(COUNTIFS($D:$D,D5,$B:$B,B5,$K:$K,K5)>1,"Duplicate","Unique") | Q5: =TEXT(B5,"mmm")
A6: INV-0005 | B6: 2025-10-02 | C6: 2025-10-17 | D6: V008 | E6: CloudWorks Software | F6: Software | G6: IT | H6: Business application | I6: 10 | J6: 583.34 | K6: 5833.38 | L6: Overdue | O6: =XLOOKUP(D6,'Vendor Mapping'!$A:$A,'Vendor Mapping'!$C:$C,"Not Found") | P6: =IF(COUNTIFS($D:$D,D6,$B:$B,B6,$K:$K,K6)>1,"Duplicate","Unique") | Q6: =TEXT(B6,"mmm")
A7: INV-0006 | B7: 2025-07-05 | C7: 2025-08-19 | D7: V010 | E7: FreshBite Catering | F7: Office Supplies | G7: Administration | H7: Printer cartridges | I7: 8 | J7: 159.49 | K7: 1275.94 | L7: Paid | M7: 2025-07-26 | N7: Bank Transfer | O7: =XLOOKUP(D7,'Vendor Mapping'!$A:$A,'Vendor Mapping'!$C:$C,"Not Found") | P7: =IF(COUNTIFS($D:$D,D7,$B:$B,B7,$K:$K,K7)>1,"Duplicate","Unique") | Q7: =TEXT(B7,"mmm")
A8: INV-0007 | B8: 2025-02-21 | C8: 2025-03-23 | D8: V004 | E8: Bright Marketing Co | F8: Marketing | G8: Marketing | H8: Printing and promotion | I8: 6 | J8: 1604.39 | K8: 9626.35 | L8: Paid | M8: 2025-03-19 | N8: Cheque | O8: =XLOOKUP(D8,'Vendor Mapping'!$A:$A,'Vendor Mapping'!$C:$C,"Not Found") | P8: =IF(COUNTIFS($D:$D,D8,$B:$B,B8,$K:$K,K8)>1,"Duplicate","Unique") | Q8: =TEXT(B8,"mmm")
A9: INV-0008 | B9: 2025-12-10 | C9: 2026-01-09 | D9: V004 | E9: Bright Marketing Co | F9: Marketing | G9: Marketing | H9: Digital advertising | I9: 20 | J9: 516.62 | K9: 10332.33 | L9: Pending | O9: =XLOOKUP(D9,'Vendor Mapping'!$A:$A,'Vendor Mapping'!$C:$C,"Not Found") | P9: =IF(COUNTIFS($D:$D,D9,$B:$B,B9,$K:$K,K9)>1,"Duplicate","Unique") | Q9: =TEXT(B9,"mmm")
A10: INV-0009 | B10: 2025-10-01 | C10: 2025-11-15 | D10: V003 | E10: CleanPro Services | F10: Facilities | G10: Facilities | H10: Maintenance | I10: 18 | J10: 392.69 | K10: 7068.34 | L10: Paid | M10: 2025-10-18 | N10: Cheque | O10: =XLOOKUP(D10,'Vendor Mapping'!$A:$A,'Vendor Mapping'!$C:$C,"Not Found") | P10: =IF(COUNTIFS($D:$D,D10,$B:$B,B10,$K:$K,K10)>1,"Duplicate","Unique") | Q10: =TEXT(B10,"mmm")
A11: INV-0010 | B11: 2025-04-28 | C11: 2025-05-13 | D11: V001 | E11: ABC Office Supplies | F11: Office Supplies | G11: Administration | H11: Printer paper | I11: 7 | J11: 881.03 | K11: 6167.18 | L11: Pending | O11: =XLOOKUP(D11,'Vendor Mapping'!$A:$A,'Vendor Mapping'!$C:$C,"Not Found") | P11: =IF(COUNTIFS($D:$D,D11,$B:$B,B11,$K:$K,K11)>1,"Duplicate","Unique") | Q11: =TEXT(B11,"mmm")
A12: INV-0011 | B12: 2025-06-11 | C12: 2025-06-26 | D12: V010 | E12: FreshBite Catering | F12: Office Supplies | G12: Administration | H12: Printer cartridges | I12: 15 | J12: 405.7 | K12: 6085.57 | L12: Pending | O12: =XLOOKUP(D12,'Vendor Mapping'!$A:$A,'Vendor Mapping'!$C:$C,"Not Found") | P12: =IF(COUNTIFS($D:$D,D12,$B:$B,B12,$K:$K,K12)>1,"Duplicate","Unique") | Q12: =TEXT(B12,"mmm")
A13: INV-0012 | B13: 2025-05-16 | C13: 2025-05-31 | D13: V003 | E13: CleanPro Services | F13: Facilities | G13: Facilities | H13: Maintenance | I13: 19 | J13: 448.96 | K13: 8530.18 | L13: Paid | M13: 2025-06-15 | N13: UPI | O13: =XLOOKUP(D13,'Vendor Mapping'!$A:$A,'Vendor Mapping'!$C:$C,"Not Found") | P13: =IF(COUNTIFS($D:$D,D13,$B:$B,B13,$K:$K,K13)>1,"Duplicate","Unique") | Q13: =TEXT(B13,"mmm")
A14: INV-0013 | B14: 2025-04-23 | C14: 2025-05-08 | D14: V006 | E14: PeopleFirst HR Services | F14: HR Services | G14: HR | H14: Recruitment service | I14: 4 | J14: 397.73 | K14: 1590.91 | L14: Paid | M14: 2025-05-05 | N14: Credit Card | O14: =XLOOKUP(D14,'Vendor Mapping'!$A:$A,'Vendor Mapping'!$C:$C,"Not Found") | P14: =IF(COUNTIFS($D:$D,D14,$B:$B,B14,$K:$K,K14)>1,"Duplicate","Unique") | Q14: =TEXT(B14,"mmm")
A15: INV-0014 | B15: 2025-11-02 | C15: 2025-11-17 | D15: V007 | E15: SafeGuard Security | F15: Facilities | G15: Facilities | H15: Maintenance | I15: 17 | J15: 531.73 | K15: 9039.35 | L15: Paid | M15: 2025-11-21 | N15: Bank Transfer | O15: =XLOOKUP(D15,'Vendor Mapping'!$A:$A,'Vendor Mapping'!$C:$C,"Not Found") | P15: =IF(COUNTIFS($D:$D,D15,$B:$B,B15,$K:$K,K15)>1,"Duplicate","Unique") | Q15: =TEXT(B15,"mmm")
A16: INV-0015 | B16: 2025-12-16 | C16: 2026-01-30 | D16: V002 | E16: Tech Solutions Ltd | F16: Software | G16: IT | H16: Cloud storage | I16: 4 | J16: 2896.71 | K16: 11586.83 | L16: Pending | O16: =XLOOKUP(D16,'Vendor Mapping'!$A:$A,'Vendor Mapping'!$C:$C,"Not Found") | P16: =IF(COUNTIFS($D:$D,D16,$B:$B,B16,$K:$K,K16)>1,"Duplicate","Unique") | Q16: =TEXT(B16,"mmm")
A17: INV-0016 | B17: 2025-08-11 | C17: 2025-08-26 | D17: V005 | E17: Metro Logistics | F17: Logistics | G17: Operations | H17: Delivery service | I17: 9 | J17: 1590.98 | K17: 14318.78 | L17: Paid | M17: 2025-09-15 | N17: Credit Card | O17: =XLOOKUP(D17,'Vendor Mapping'!$A:$A,'Vendor Mapping'!$C:$C,"Not Found") | P17: =IF(COUNTIFS($D:$D,D17,$B:$B,B17,$K:$K,K17)>1,"Duplicate","Unique") | Q17: =TEXT(B17,"mmm")
A18: INV-0017 | B18: 2025-02-24 | C18: 2025-04-10 | D18: V009 | E18: Prime Travel Services | F18: Travel | G18: Operations | H18: Travel expenses | I18: 7 | J18: 1382.07 | K18: 9674.51 | L18: Paid | M18: 2025-03-08 | N18: Cheque | O18: =XLOOKUP(D18,'Vendor Mapping'!$A:$A,'Vendor Mapping'!$C:$C,"Not Found") | P18: =IF(COUNTIFS($D:$D,D18,$B:$B,B18,$K:$K,K18)>1,"Duplicate","Unique") | Q18: =TEXT(B18,"mmm")
A19: INV-0018 | B19: 2025-10-04 | C19: 2025-11-18 | D19: V003 | E19: CleanPro Services | F19: Facilities | G19: Facilities | H19: Maintenance | I19: 1 | J19: 9084.43 | K19: 9084.43 | L19: Overdue | O19: =XLOOKUP(D19,'Vendor Mapping'!$A:$A,'Vendor Mapping'!$C:$C,"Not Found") | P19: =IF(COUNTIFS($D:$D,D19,$B:$B,B19,$K:$K,K19)>1,"Duplicate","Unique") | Q19: =TEXT(B19,"mmm")
A20: INV-0019 | B20: 2025-07-05 | C20: 2025-08-04 | D20: V002 | E20: Tech Solutions Ltd | F20: Software | G20: IT | H20: Business application | I20: 3 | J20: 1267.62 | K20: 3802.86 | L20: Paid | M20: 2025-07-13 | N20: UPI | O20: =XLOOKUP(D20,'Vendor Mapping'!$A:$A,'Vendor Mapping'!$C:$C,"Not Found") | P20: =IF(COUNTIFS($D:$D,D20,$B:$B,B20,$K:$K,K20)>1,"Duplicate","Unique") | Q20: =TEXT(B20,"mmm")
A21: INV-0020 | B21: 2025-09-30 | C21: 2025-10-15 | D21: V002 | E21: Tech Solutions Ltd | F21: Software | G21: IT | H21: Business application | I21: 6 | J21: 1210.07 | K21: 7260.42 | L21: Paid | M21: 2025-10-19 | N21: UPI | O21: =XLOOKUP(D21,'Vendor Mapping'!$A:$A,'Vendor Mapping'!$C:$C,"Not Found") | P21: =IF(COUNTIFS($D:$D,D21,$B:$B,B21,$K:$K,K21)>1,"Duplicate","Unique") | Q21: =TEXT(B21,"mmm")
A22: INV-0021 | B22: 2025-10-04 | C22: 2025-11-18 | D22: V004 | E22: Bright Marketing Co | F22: Marketing | G22: Marketing | H22: Printing and promotion | I22: 12 | J22: 897.17 | K22: 10766 | L22: Pending | O22: =XLOOKUP(D22,'Vendor Mapping'!$A:$A,'Vendor Mapping'!$C:$C,"Not Found") | P22: =IF(COUNTIFS($D:$D,D22,$B:$B,B22,$K:$K,K22)>1,"Duplicate","Unique") | Q22: =TEXT(B22,"mmm")
A23: INV-0022 | B23: 2025-09-22 | C23: 2025-10-22 | D23: V008 | E23: CloudWorks Software | F23: Software | G23: IT | H23: Cloud storage | I23: 1 | J23: 3564.29 | K23: 3564.29 | L23: Paid | M23: 2025-10-09 | N23: Credit Card | O23: =XLOOKUP(D23,'Vendor Mapping'!$A:$A,'Vendor Mapping'!$C:$C,"Not Found") | P23: =IF(COUNTIFS($D:$D,D23,$B:$B,B23,$K:$K,K23)>1,"Duplicate","Unique") | Q23: =TEXT(B23,"mmm")
A24: INV-0023 | B24: 2025-02-06 | C24: 2025-03-23 | D24: V001 | E24: ABC Office Supplies | F24: Office Supplies | G24: Administration | H24: Printer paper | I24: 11 | J24: 329.72 | K24: 3626.89 | L24: Pending | O24: =XLOOKUP(D24,'Vendor Mapping'!$A:$A,'Vendor Mapping'!$C:$C,"Not Found") | P24: =IF(COUNTIFS($D:$D,D24,$B:$B,B24,$K:$K,K24)>1,"Duplicate","Unique") | Q24: =TEXT(B24,"mmm")
A25: INV-0024 | B25: 2025-09-21 | C25: 2025-10-06 | D25: V002 | E25: Tech Solutions Ltd | F25: Software | G25: IT | H25: Business application | I25: 5 | J25: 1481.97 | K25: 7409.86 | L25: Paid | M25: 2025-10-24 | N25: Credit Card | O25: =XLOOKUP(D25,'Vendor Mapping'!$A:$A,'Vendor Mapping'!$C:$C,"Not Found") | P25: =IF(COUNTIFS($D:$D,D25,$B:$B,B25,$K:$K,K25)>1,"Duplicate","Unique") | Q25: =TEXT(B25,"mmm")
A26: INV-0025 | B26: 2025-07-28 | C26: 2025-08-12 | D26: V008 | E26: CloudWorks Software | F26: Software | G26: IT | H26: Cloud storage | I26: 14 | J26: 712.14 | K26: 9970 | L26: Paid | M26: 2025-08-26 | N26: UPI | O26: =XLOOKUP(D26,'Vendor Mapping'!$A:$A,'Vendor Mapping'!$C:$C,"Not Found") | P26: =IF(COUNTIFS($D:$D,D26,$B:$B,B26,$K:$K,K26)>1,"Duplicate","Unique") | Q26: =TEXT(B26,"mmm")
A27: INV-0026 | B27: 2025-12-11 | C27: 2026-01-25 | D27: V001 | E27: ABC Office Supplies | F27: Office Supplies | G27: Administration | H27: Pens and stationery | I27: 11 | J27: 154.7 | K27: 1701.66 | L27: Overdue | O27: =XLOOKUP(D27,'Vendor Mapping'!$A:$A,'Vendor Mapping'!$C:$C,"Not Found") | P27: =IF(COUNTIFS($D:$D,D27,$B:$B,B27,$K:$K,K27)>1,"Duplicate","Unique") | Q27: =TEXT(B27,"mmm")
A28: INV-0027 | B28: 2025-05-08 | C28: 2025-05-23 | D28: V002 | E28: Tech Solutions Ltd | F28: Software | G28: IT | H28: Cloud storage | I28: 6 | J28: 1144.51 | K28: 6867.05 | L28: Paid | M28: 2025-05-28 | N28: UPI | O28: =XLOOKUP(D28,'Vendor Mapping'!$A:$A,'Vendor Mapping'!$C:$C,"Not Found") | P28: =IF(COUNTIFS($D:$D,D28,$B:$B,B28,$K:$K,K28)>1,"Duplicate","Unique") | Q28: =TEXT(B28,"mmm")
A29: INV-0028 | B29: 2025-02-08 | C29: 2025-03-10 | D29: V004 | E29: Bright Marketing Co | F29: Marketing | G29: Marketing | H29: Digital advertising | I29: 2 | J29: 6437.76 | K29: 12875.51 | L29: Pending | O29: =XLOOKUP(D29,'Vendor Mapping'!$A:$A,'Vendor Mapping'!$C:$C,"Not Found") | P29: =IF(COUNTIFS($D:$D,D29,$B:$B,B29,$K:$K,K29)>1,"Duplicate","Unique") | Q29: =TEXT(B29,"mmm")
A30: INV-0029 | B30: 2025-01-08 | C30: 2025-01-23 | D30: V009 | E30: Prime Travel Services | F30: Travel | G30: Operations | H30: Flight booking | I30: 14 | J30: 912.02 | K30: 12768.26 | L30: Overdue | O30: =XLOOKUP(D30,'Vendor Mapping'!$A:$A,'Vendor Mapping'!$C:$C,"Not Found") | P30: =IF(COUNTIFS($D:$D,D30,$B:$B,B30,$K:$K,K30)>1,"Duplicate","Unique") | Q30: =TEXT(B30,"mmm")
A31: INV-0030 | B31: 2025-09-04 | C31: 2025-09-19 | D31: V008 | E31: CloudWorks Software | F31: Software | G31: IT | H31: Software subscription | I31: 13 | J31: 1043.16 | K31: 13561.03 | L31: Overdue | O31: =XLOOKUP(D31,'Vendor Mapping'!$A:$A,'Vendor Mapping'!$C:$C,"Not Found") | P31: =IF(COUNTIFS($D:$D,D31,$B:$B,B31,$K:$K,K31)>1,"Duplicate","Unique") | Q31: =TEXT(B31,"mmm")
A32: INV-0031 | B32: 2025-07-19 | C32: 2025-08-18 | D32: V001 | E32: ABC Office Supplies | F32: Office Supplies | G32: Administration | H32: Pens and stationery | I32: 14 | J32: 845.05 | K32: 11830.66 | L32: Overdue | O32: =XLOOKUP(D32,'Vendor Mapping'!$A:$A,'Vendor Mapping'!$C:$C,"Not Found") | P32: =IF(COUNTIFS($D:$D,D32,$B:$B,B32,$K:$K,K32)>1,"Duplicate","Unique") | Q32: =TEXT(B32,"mmm")
A33: INV-0032 | B33: 2025-12-05 | C33: 2026-01-19 | D33: V009 | E33: Prime Travel Services | F33: Travel | G33: Operations | H33: Flight booking | I33: 2 | J33: 1525.49 | K33: 3050.99 | L33: Paid | M33: 2025-12-11 | N33: Cheque | O33: =XLOOKUP(D33,'Vendor Mapping'!$A:$A,'Vendor Mapping'!$C:$C,"Not Found") | P33: =IF(COUNTIFS($D:$D,D33,$B:$B,B33,$K:$K,K33)>1,"Duplicate","Unique") | Q33: =TEXT(B33,"mmm")
A34: INV-0033 | B34: 2025-01-26 | C34: 2025-03-12 | D34: V001 | E34: ABC Office Supplies | F34: Office Supplies | G34: Administration | H34: Printer cartridges | I34: 6 | J34: 2301.83 | K34: 13810.96 | L34: Paid | M34: 2025-02-01 | N34: Bank Transfer | O34: =XLOOKUP(D34,'Vendor Mapping'!$A:$A,'Vendor Mapping'!$C:$C,"Not Found") | P34: =IF(COUNTIFS($D:$D,D34,$B:$B,B34,$K:$K,K34)>1,"Duplicate","Unique") | Q34: =TEXT(B34,"mmm")
A35: INV-0034 | B35: 2025-02-05 | C35: 2025-03-22 | D35: V003 | E35: CleanPro Services | F35: Facilities | G35: Facilities | H35: Maintenance | I35: 4 | J35: 3240.46 | K35: 12961.83 | L35: Paid | M35: 2025-02-23 | N35: Bank Transfer | O35: =XLOOKUP(D35,'Vendor Mapping'!$A:$A,'Vendor Mapping'!$C:$C,"Not Found") | P35: =IF(COUNTIFS($D:$D,D35,$B:$B,B35,$K:$K,K35)>1,"Duplicate","Unique") | Q35: =TEXT(B35,"mmm")
A36: INV-0035 | B36: 2025-02-11 | C36: 2025-03-13 | D36: V010 | E36: FreshBite Catering | F36: Office Supplies | G36: Administration | H36: Pens and stationery | I36: 9 | J36: 954.12 | K36: 8587.1 | L36: Pending | O36: =XLOOKUP(D36,'Vendor Mapping'!$A:$A,'Vendor Mapping'!$C:$C,"Not Found") | P36: =IF(COUNTIFS($D:$D,D36,$B:$B,B36,$K:$K,K36)>1,"Duplicate","Unique") | Q36: =TEXT(B36,"mmm")
A37: INV-0036 | B37: 2025-12-09 | C37: 2026-01-23 | D37: V004 | E37: Bright Marketing Co | F37: Marketing | G37: Marketing | H37: Digital advertising | I37: 10 | J37: 416.78 | K37: 4167.81 | L37: Paid | M37: 2026-01-10 | N37: Cheque | O37: =XLOOKUP(D37,'Vendor Mapping'!$A:$A,'Vendor Mapping'!$C:$C,"Not Found") | P37: =IF(COUNTIFS($D:$D,D37,$B:$B,B37,$K:$K,K37)>1,"Duplicate","Unique") | Q37: =TEXT(B37,"mmm")
A38: INV-0037 | B38: 2025-01-05 | C38: 2025-02-04 | D38: V002 | E38: Tech Solutions Ltd | F38: Software | G38: IT | H38: Software subscription | I38: 3 | J38: 2851.39 | K38: 8554.16 | L38: Pending | O38: =XLOOKUP(D38,'Vendor Mapping'!$A:$A,'Vendor Mapping'!$C:$C,"Not Found") | P38: =IF(COUNTIFS($D:$D,D38,$B:$B,B38,$K:$K,K38)>1,"Duplicate","Unique") | Q38: =TEXT(B38,"mmm")
A39: INV-0038 | B39: 2025-04-20 | C39: 2025-06-04 | D39: V009 | E39: Prime Travel Services | F39: Travel | G39: Operations | H39: Flight booking | I39: 8 | J39: 1751.95 | K39: 14015.58 | L39: Paid | M39: 2025-05-16 | N39: Cheque | O39: =XLOOKUP(D39,'Vendor Mapping'!$A:$A,'Vendor Mapping'!$C:$C,"Not Found") | P39: =IF(COUNTIFS($D:$D,D39,$B:$B,B39,$K:$K,K39)>1,"Duplicate","Unique") | Q39: =TEXT(B39,"mmm")
A40: INV-0039 | B40: 2025-08-13 | C40: 2025-09-27 | D40: V003 | E40: CleanPro Services | F40: Facilities | G40: Facilities | H40: Security service | I40: 17 | J40: 545.43 | K40: 9272.25 | L40: Pending | O40: =XLOOKUP(D40,'Vendor Mapping'!$A:$A,'Vendor Mapping'!$C:$C,"Not Found") | P40: =IF(COUNTIFS($D:$D,D40,$B:$B,B40,$K:$K,K40)>1,"Duplicate","Unique") | Q40: =TEXT(B40,"mmm")
A41: INV-0040 | B41: 2025-12-08 | C41: 2026-01-22 | D41: V001 | E41: ABC Office Supplies | F41: Office Supplies | G41: Administration | H41: Printer paper | I41: 9 | J41: 1115 | K41: 10034.98 | L41: Paid | M41: 2025-12-18 | N41: Bank Transfer | O41: =XLOOKUP(D41,'Vendor Mapping'!$A:$A,'Vendor Mapping'!$C:$C,"Not Found") | P41: =IF(COUNTIFS($D:$D,D41,$B:$B,B41,$K:$K,K41)>1,"Duplicate","Unique") | Q41: =TEXT(B41,"mmm")
A42: INV-0041 | B42: 2025-03-21 | C42: 2025-04-20 | D42: V009 | E42: Prime Travel Services | F42: Travel | G42: Operations | H42: Hotel accommodation | I42: 7 | J42: 479.54 | K42: 3356.79 | L42: Paid | M42: 2025-04-09 | N42: UPI | O42: =XLOOKUP(D42,'Vendor Mapping'!$A:$A,'Vendor Mapping'!$C:$C,"Not Found") | P42: =IF(COUNTIFS($D:$D,D42,$B:$B,B42,$K:$K,K42)>1,"Duplicate","Unique") | Q42: =TEXT(B42,"mmm")
A43: INV-0042 | B43: 2025-01-27 | C43: 2025-02-11 | D43: V005 | E43: Metro Logistics | F43: Logistics | G43: Operations | H43: Courier service | I43: 1 | J43: 12482.88 | K43: 12482.88 | L43: Pending | O43: =XLOOKUP(D43,'Vendor Mapping'!$A:$A,'Vendor Mapping'!$C:$C,"Not Found") | P43: =IF(COUNTIFS($D:$D,D43,$B:$B,B43,$K:$K,K43)>1,"Duplicate","Unique") | Q43: =TEXT(B43,"mmm")
A44: INV-0043 | B44: 2025-03-08 | C44: 2025-04-22 | D44: V006 | E44: PeopleFirst HR Services | F44: HR Services | G44: HR | H44: Training service | I44: 18 | J44: 146.3 | K44: 2633.33 | L44: Overdue | O44: =XLOOKUP(D44,'Vendor Mapping'!$A:$A,'Vendor Mapping'!$C:$C,"Not Found") | P44: =IF(COUNTIFS($D:$D,D44,$B:$B,B44,$K:$K,K44)>1,"Duplicate","Unique") | Q44: =TEXT(B44,"mmm")
A45: INV-0044 | B45: 2025-10-15 | C45: 2025-10-30 | D45: V007 | E45: SafeGuard Security | F45: Facilities | G45: Facilities | H45: Security service | I45: 5 | J45: 2837.9 | K45: 14189.5 | L45: Paid | M45: 2025-10-20 | N45: Cheque | O45: =XLOOKUP(D45,'Vendor Mapping'!$A:$A,'Vendor Mapping'!$C:$C,"Not Found") | P45: =IF(COUNTIFS($D:$D,D45,$B:$B,B45,$K:$K,K45)>1,"Duplicate","Unique") | Q45: =TEXT(B45,"mmm")
A46: INV-0045 | B46: 2025-10-10 | C46: 2025-10-25 | D46: V010 | E46: FreshBite Catering | F46: Office Supplies | G46: Administration | H46: Pens and stationery | I46: 2 | J46: 433.49 | K46: 866.98 | L46: Paid | M46: 2025-11-04 | N46: Credit Card | O46: =XLOOKUP(D46,'Vendor Mapping'!$A:$A,'Vendor Mapping'!$C:$C,"Not Found") | P46: =IF(COUNTIFS($D:$D,D46,$B:$B,B46,$K:$K,K46)>1,"Duplicate","Unique") | Q46: =TEXT(B46,"mmm")
A47: INV-0046 | B47: 2025-12-08 | C47: 2025-12-23 | D47: V004 | E47: Bright Marketing Co | F47: Marketing | G47: Marketing | H47: Printing and promotion | I47: 20 | J47: 425.41 | K47: 8508.28 | L47: Paid | M47: 2025-12-20 | N47: Credit Card | O47: =XLOOKUP(D47,'Vendor Mapping'!$A:$A,'Vendor Mapping'!$C:$C,"Not Found") | P47: =IF(COUNTIFS($D:$D,D47,$B:$B,B47,$K:$K,K47)>1,"Duplicate","Unique") | Q47: =TEXT(B47,"mmm")
A48: INV-0047 | B48: 2025-04-01 | C48: 2025-05-01 | D48: V003 | E48: CleanPro Services | F48: Facilities | G48: Facilities | H48: Maintenance | I48: 14 | J48: 793.88 | K48: 11114.33 | L48: Paid | M48: 2025-04-19 | N48: Cheque | O48: =XLOOKUP(D48,'Vendor Mapping'!$A:$A,'Vendor Mapping'!$C:$C,"Not Found") | P48: =IF(COUNTIFS($D:$D,D48,$B:$B,B48,$K:$K,K48)>1,"Duplicate","Unique") | Q48: =TEXT(B48,"mmm")
A49: INV-0048 | B49: 2025-12-26 | C49: 2026-01-10 | D49: V003 | E49: CleanPro Services | F49: Facilities | G49: Facilities | H49: Maintenance | I49: 8 | J49: 102.65 | K49: 821.19 | L49: Paid | M49: 2026-01-10 | N49: UPI | O49: =XLOOKUP(D49,'Vendor Mapping'!$A:$A,'Vendor Mapping'!$C:$C,"Not Found") | P49: =IF(COUNTIFS($D:$D,D49,$B:$B,B49,$K:$K,K49)>1,"Duplicate","Unique") | Q49: =TEXT(B49,"mmm")
A50: INV-0049 | B50: 2025-06-06 | C50: 2025-06-21 | D50: V006 | E50: PeopleFirst HR Services | F50: HR Services | G50: HR | H50: Training service | I50: 11 | J50: 907.77 | K50: 9985.49 | L50: Paid | M50: 2025-06-26 | N50: Bank Transfer | O50: =XLOOKUP(D50,'Vendor Mapping'!$A:$A,'Vendor Mapping'!$C:$C,"Not Found") | P50: =IF(COUNTIFS($D:$D,D50,$B:$B,B50,$K:$K,K50)>1,"Duplicate","Unique") | Q50: =TEXT(B50,"mmm")
A51: INV-0050 | B51: 2025-06-29 | C51: 2025-08-13 | D51: V005 | E51: Metro Logistics | F51: Logistics | G51: Operations | H51: Delivery service | I51: 11 | J51: 933.9 | K51: 10272.89 | L51: Paid | M51: 2025-07-03 | N51: Bank Transfer | O51: =XLOOKUP(D51,'Vendor Mapping'!$A:$A,'Vendor Mapping'!$C:$C,"Not Found") | P51: =IF(COUNTIFS($D:$D,D51,$B:$B,B51,$K:$K,K51)>1,"Duplicate","Unique") | Q51: =TEXT(B51,"mmm")
A52: INV-0051 | B52: 2025-04-02 | C52: 2025-05-17 | D52: V005 | E52: Metro Logistics | F52: Logistics | G52: Operations | H52: Courier service | I52: 20 | J52: 208.28 | K52: 4165.63 | L52: Overdue | O52: =XLOOKUP(D52,'Vendor Mapping'!$A:$A,'Vendor Mapping'!$C:$C,"Not Found") | P52: =IF(COUNTIFS($D:$D,D52,$B:$B,B52,$K:$K,K52)>1,"Duplicate","Unique") | Q52: =TEXT(B52,"mmm")
A53: INV-0052 | B53: 2025-06-26 | C53: 2025-08-10 | D53: V007 | E53: SafeGuard Security | F53: Facilities | G53: Facilities | H53: Security service | I53: 4 | J53: 1671.7 | K53: 6686.81 | L53: Pending | O53: =XLOOKUP(D53,'Vendor Mapping'!$A:$A,'Vendor Mapping'!$C:$C,"Not Found") | P53: =IF(COUNTIFS($D:$D,D53,$B:$B,B53,$K:$K,K53)>1,"Duplicate","Unique") | Q53: =TEXT(B53,"mmm")
A54: INV-0053 | B54: 2025-10-23 | C54: 2025-11-07 | D54: V007 | E54: SafeGuard Security | F54: Facilities | G54: Facilities | H54: Cleaning service | I54: 17 | J54: 629.68 | K54: 10704.58 | L54: Paid | M54: 2025-11-07 | N54: Cheque | O54: =XLOOKUP(D54,'Vendor Mapping'!$A:$A,'Vendor Mapping'!$C:$C,"Not Found") | P54: =IF(COUNTIFS($D:$D,D54,$B:$B,B54,$K:$K,K54)>1,"Duplicate","Unique") | Q54: =TEXT(B54,"mmm")
A55: INV-0054 | B55: 2025-02-05 | C55: 2025-03-22 | D55: V007 | E55: SafeGuard Security | F55: Facilities | G55: Facilities | H55: Security service | I55: 4 | J55: 2360.39 | K55: 9441.54 | L55: Overdue | O55: =XLOOKUP(D55,'Vendor Mapping'!$A:$A,'Vendor Mapping'!$C:$C,"Not Found") | P55: =IF(COUNTIFS($D:$D,D55,$B:$B,B55,$K:$K,K55)>1,"Duplicate","Unique") | Q55: =TEXT(B55,"mmm")
A56: INV-0055 | B56: 2025-09-17 | C56: 2025-10-17 | D56: V005 | E56: Metro Logistics | F56: Logistics | G56: Operations | H56: Delivery service | I56: 10 | J56: 506.12 | K56: 5061.2 | L56: Pending | O56: =XLOOKUP(D56,'Vendor Mapping'!$A:$A,'Vendor Mapping'!$C:$C,"Not Found") | P56: =IF(COUNTIFS($D:$D,D56,$B:$B,B56,$K:$K,K56)>1,"Duplicate","Unique") | Q56: =TEXT(B56,"mmm")
A57: INV-0056 | B57: 2025-03-07 | C57: 2025-03-22 | D57: V009 | E57: Prime Travel Services | F57: Travel | G57: Operations | H57: Travel expenses | I57: 6 | J57: 2353.39 | K57: 14120.36 | L57: Paid | M57: 2025-03-29 | N57: UPI | O57: =XLOOKUP(D57,'Vendor Mapping'!$A:$A,'Vendor Mapping'!$C:$C,"Not Found") | P57: =IF(COUNTIFS($D:$D,D57,$B:$B,B57,$K:$K,K57)>1,"Duplicate","Unique") | Q57: =TEXT(B57,"mmm")
A58: INV-0057 | B58: 2025-01-01 | C58: 2025-01-31 | D58: V009 | E58: Prime Travel Services | F58: Travel | G58: Operations | H58: Travel expenses | I58: 20 | J58: 329.54 | K58: 6590.85 | L58: Paid | M58: 2025-01-24 | N58: UPI | O58: =XLOOKUP(D58,'Vendor Mapping'!$A:$A,'Vendor Mapping'!$C:$C,"Not Found") | P58: =IF(COUNTIFS($D:$D,D58,$B:$B,B58,$K:$K,K58)>1,"Duplicate","Unique") | Q58: =TEXT(B58,"mmm")
A59: INV-0058 | B59: 2025-08-15 | C59: 2025-09-29 | D59: V008 | E59: CloudWorks Software | F59: Software | G59: IT | H59: Business application | I59: 6 | J59: 1204.92 | K59: 7229.5 | L59: Paid | M59: 2025-08-23 | N59: Cheque | O59: =XLOOKUP(D59,'Vendor Mapping'!$A:$A,'Vendor Mapping'!$C:$C,"Not Found") | P59: =IF(COUNTIFS($D:$D,D59,$B:$B,B59,$K:$K,K59)>1,"Duplicate","Unique") | Q59: =TEXT(B59,"mmm")
A60: INV-0059 | B60: 2025-12-06 | C60: 2026-01-20 | D60: V009 | E60: Prime Travel Services | F60: Travel | G60: Operations | H60: Flight booking | I60: 10 | J60: 162.75 | K60: 1627.46 | L60: Pending | O60: =XLOOKUP(D60,'Vendor Mapping'!$A:$A,'Vendor Mapping'!$C:$C,"Not Found") | P60: =IF(COUNTIFS($D:$D,D60,$B:$B,B60,$K:$K,K60)>1,"Duplicate","Unique") | Q60: =TEXT(B60,"mmm")
A61: INV-0060 | B61: 2025-04-12 | C61: 2025-04-27 | D61: V004 | E61: Bright Marketing Co | F61: Marketing | G61: Marketing | H61: Printing and promotion | I61: 20 | J61: 193.07 | K61: 3861.43 | L61: Paid | M61: 2025-04-19 | N61: UPI | O61: =XLOOKUP(D61,'Vendor Mapping'!$A:$A,'Vendor Mapping'!$C:$C,"Not Found") | P61: =IF(COUNTIFS($D:$D,D61,$B:$B,B61,$K:$K,K61)>1,"Duplicate","Unique") | Q61: =TEXT(B61,"mmm")
A62: INV-0061 | B62: 2025-11-19 | C62: 2026-01-03 | D62: V007 | E62: SafeGuard Security | F62: Facilities | G62: Facilities | H62: Maintenance | I62: 13 | J62: 809.33 | K62: 10521.23 | L62: Paid | M62: 2025-12-07 | N62: Credit Card | O62: =XLOOKUP(D62,'Vendor Mapping'!$A:$A,'Vendor Mapping'!$C:$C,"Not Found") | P62: =IF(COUNTIFS($D:$D,D62,$B:$B,B62,$K:$K,K62)>1,"Duplicate","Unique") | Q62: =TEXT(B62,"mmm")
A63: INV-0062 | B63: 2025-02-24 | C63: 2025-03-26 | D63: V001 | E63: ABC Office Supplies | F63: Office Supplies | G63: Administration | H63: Printer cartridges | I63: 17 | J63: 712.39 | K63: 12110.62 | L63: Paid | M63: 2025-03-28 | N63: Bank Transfer | O63: =XLOOKUP(D63,'Vendor Mapping'!$A:$A,'Vendor Mapping'!$C:$C,"Not Found") | P63: =IF(COUNTIFS($D:$D,D63,$B:$B,B63,$K:$K,K63)>1,"Duplicate","Unique") | Q63: =TEXT(B63,"mmm")
A64: INV-0063 | B64: 2025-05-08 | C64: 2025-05-23 | D64: V009 | E64: Prime Travel Services | F64: Travel | G64: Operations | H64: Travel expenses | I64: 17 | J64: 710.05 | K64: 12070.89 | L64: Paid | M64: 2025-05-31 | N64: UPI | O64: =XLOOKUP(D64,'Vendor Mapping'!$A:$A,'Vendor Mapping'!$C:$C,"Not Found") | P64: =IF(COUNTIFS($D:$D,D64,$B:$B,B64,$K:$K,K64)>1,"Duplicate","Unique") | Q64: =TEXT(B64,"mmm")
A65: INV-0064 | B65: 2025-09-16 | C65: 2025-10-16 | D65: V010 | E65: FreshBite Catering | F65: Office Supplies | G65: Administration | H65: Printer paper | I65: 16 | J65: 520.69 | K65: 8331.11 | L65: Pending | O65: =XLOOKUP(D65,'Vendor Mapping'!$A:$A,'Vendor Mapping'!$C:$C,"Not Found") | P65: =IF(COUNTIFS($D:$D,D65,$B:$B,B65,$K:$K,K65)>1,"Duplicate","Unique") | Q65: =TEXT(B65,"mmm")
A66: INV-0065 | B66: 2025-05-13 | C66: 2025-05-28 | D66: V008 | E66: CloudWorks Software | F66: Software | G66: IT | H66: Business application | I66: 16 | J66: 271.27 | K66: 4340.34 | L66: Pending | O66: =XLOOKUP(D66,'Vendor Mapping'!$A:$A,'Vendor Mapping'!$C:$C,"Not Found") | P66: =IF(COUNTIFS($D:$D,D66,$B:$B,B66,$K:$K,K66)>1,"Duplicate","Unique") | Q66: =TEXT(B66,"mmm")
A67: INV-0066 | B67: 2025-05-21 | C67: 2025-06-20 | D67: V004 | E67: Bright Marketing Co | F67: Marketing | G67: Marketing | H67: Printing and promotion | I67: 11 | J67: 405.86 | K67: 4464.49 | L67: Paid | M67: 2025-06-13 | N67: Bank Transfer | O67: =XLOOKUP(D67,'Vendor Mapping'!$A:$A,'Vendor Mapping'!$C:$C,"Not Found") | P67: =IF(COUNTIFS($D:$D,D67,$B:$B,B67,$K:$K,K67)>1,"Duplicate","Unique") | Q67: =TEXT(B67,"mmm")
A68: INV-0067 | B68: 2025-03-19 | C68: 2025-04-03 | D68: V003 | E68: CleanPro Services | F68: Facilities | G68: Facilities | H68: Cleaning service | I68: 3 | J68: 834.63 | K68: 2503.88 | L68: Paid | M68: 2025-04-17 | N68: UPI | O68: =XLOOKUP(D68,'Vendor Mapping'!$A:$A,'Vendor Mapping'!$C:$C,"Not Found") | P68: =IF(COUNTIFS($D:$D,D68,$B:$B,B68,$K:$K,K68)>1,"Duplicate","Unique") | Q68: =TEXT(B68,"mmm")
A69: INV-0068 | B69: 2025-10-05 | C69: 2025-11-04 | D69: V006 | E69: PeopleFirst HR Services | F69: HR Services | G69: HR | H69: Training service | I69: 13 | J69: 253.91 | K69: 3300.81 | L69: Paid | M69: 2025-10-09 | N69: UPI | O69: =XLOOKUP(D69,'Vendor Mapping'!$A:$A,'Vendor Mapping'!$C:$C,"Not Found") | P69: =IF(COUNTIFS($D:$D,D69,$B:$B,B69,$K:$K,K69)>1,"Duplicate","Unique") | Q69: =TEXT(B69,"mmm")
A70: INV-0069 | B70: 2025-01-04 | C70: 2025-02-03 | D70: V008 | E70: CloudWorks Software | F70: Software | G70: IT | H70: Cloud storage | I70: 18 | J70: 333.46 | K70: 6002.3 | L70: Paid | M70: 2025-01-21 | N70: UPI | O70: =XLOOKUP(D70,'Vendor Mapping'!$A:$A,'Vendor Mapping'!$C:$C,"Not Found") | P70: =IF(COUNTIFS($D:$D,D70,$B:$B,B70,$K:$K,K70)>1,"Duplicate","Unique") | Q70: =TEXT(B70,"mmm")
A71: INV-0070 | B71: 2025-05-20 | C71: 2025-06-19 | D71: V004 | E71: Bright Marketing Co | F71: Marketing | G71: Marketing | H71: Marketing services | I71: 13 | J71: 460.43 | K71: 5985.64 | L71: Paid | M71: 2025-06-02 | N71: UPI | O71: =XLOOKUP(D71,'Vendor Mapping'!$A:$A,'Vendor Mapping'!$C:$C,"Not Found") | P71: =IF(COUNTIFS($D:$D,D71,$B:$B,B71,$K:$K,K71)>1,"Duplicate","Unique") | Q71: =TEXT(B71,"mmm")
A72: INV-0071 | B72: 2025-11-15 | C72: 2025-12-30 | D72: V003 | E72: CleanPro Services | F72: Facilities | G72: Facilities | H72: Security service | I72: 1 | J72: 6061.8 | K72: 6061.8 | L72: Paid | M72: 2025-11-23 | N72: UPI | O72: =XLOOKUP(D72,'Vendor Mapping'!$A:$A,'Vendor Mapping'!$C:$C,"Not Found") | P72: =IF(COUNTIFS($D:$D,D72,$B:$B,B72,$K:$K,K72)>1,"Duplicate","Unique") | Q72: =TEXT(B72,"mmm")
A73: INV-0072 | B73: 2025-08-25 | C73: 2025-09-09 | D73: V003 | E73: CleanPro Services | F73: Facilities | G73: Facilities | H73: Cleaning service | I73: 15 | J73: 389.45 | K73: 5841.78 | L73: Paid | M73: 2025-09-17 | N73: Cheque | O73: =XLOOKUP(D73,'Vendor Mapping'!$A:$A,'Vendor Mapping'!$C:$C,"Not Found") | P73: =IF(COUNTIFS($D:$D,D73,$B:$B,B73,$K:$K,K73)>1,"Duplicate","Unique") | Q73: =TEXT(B73,"mmm")
A74: INV-0073 | B74: 2025-05-23 | C74: 2025-06-22 | D74: V007 | E74: SafeGuard Security | F74: Facilities | G74: Facilities | H74: Cleaning service | I74: 18 | J74: 81.01 | K74: 1458.12 | L74: Paid | M74: 2025-05-29 | N74: Cheque | O74: =XLOOKUP(D74,'Vendor Mapping'!$A:$A,'Vendor Mapping'!$C:$C,"Not Found") | P74: =IF(COUNTIFS($D:$D,D74,$B:$B,B74,$K:$K,K74)>1,"Duplicate","Unique") | Q74: =TEXT(B74,"mmm")
A75: INV-0074 | B75: 2025-11-29 | C75: 2025-12-14 | D75: V004 | E75: Bright Marketing Co | F75: Marketing | G75: Marketing | H75: Digital advertising | I75: 8 | J75: 1232.92 | K75: 9863.38 | L75: Pending | O75: =XLOOKUP(D75,'Vendor Mapping'!$A:$A,'Vendor Mapping'!$C:$C,"Not Found") | P75: =IF(COUNTIFS($D:$D,D75,$B:$B,B75,$K:$K,K75)>1,"Duplicate","Unique") | Q75: =TEXT(B75,"mmm")
A76: INV-0075 | B76: 2025-01-11 | C76: 2025-02-25 | D76: V004 | E76: Bright Marketing Co | F76: Marketing | G76: Marketing | H76: Marketing services | I76: 4 | J76: 527.94 | K76: 2111.76 | L76: Paid | M76: 2025-01-27 | N76: UPI | O76: =XLOOKUP(D76,'Vendor Mapping'!$A:$A,'Vendor Mapping'!$C:$C,"Not Found") | P76: =IF(COUNTIFS($D:$D,D76,$B:$B,B76,$K:$K,K76)>1,"Duplicate","Unique") | Q76: =TEXT(B76,"mmm")
A77: INV-0076 | B77: 2025-07-08 | C77: 2025-07-23 | D77: V005 | E77: Metro Logistics | F77: Logistics | G77: Operations | H77: Delivery service | I77: 4 | J77: 3616.27 | K77: 14465.09 | L77: Pending | O77: =XLOOKUP(D77,'Vendor Mapping'!$A:$A,'Vendor Mapping'!$C:$C,"Not Found") | P77: =IF(COUNTIFS($D:$D,D77,$B:$B,B77,$K:$K,K77)>1,"Duplicate","Unique") | Q77: =TEXT(B77,"mmm")
A78: INV-0077 | B78: 2025-06-09 | C78: 2025-06-24 | D78: V003 | E78: CleanPro Services | F78: Facilities | G78: Facilities | H78: Security service | I78: 13 | J78: 1073.16 | K78: 13951.09 | L78: Paid | M78: 2025-07-07 | N78: Credit Card | O78: =XLOOKUP(D78,'Vendor Mapping'!$A:$A,'Vendor Mapping'!$C:$C,"Not Found") | P78: =IF(COUNTIFS($D:$D,D78,$B:$B,B78,$K:$K,K78)>1,"Duplicate","Unique") | Q78: =TEXT(B78,"mmm")
A79: INV-0078 | B79: 2025-10-31 | C79: 2025-12-15 | D79: V002 | E79: Tech Solutions Ltd | F79: Software | G79: IT | H79: Business application | I79: 10 | J79: 383.2 | K79: 3832.03 | L79: Pending | O79: =XLOOKUP(D79,'Vendor Mapping'!$A:$A,'Vendor Mapping'!$C:$C,"Not Found") | P79: =IF(COUNTIFS($D:$D,D79,$B:$B,B79,$K:$K,K79)>1,"Duplicate","Unique") | Q79: =TEXT(B79,"mmm")
A80: INV-0079 | B80: 2025-03-03 | C80: 2025-04-17 | D80: V010 | E80: FreshBite Catering | F80: Office Supplies | G80: Administration | H80: Pens and stationery | I80: 12 | J80: 447.61 | K80: 5371.26 | L80: Pending | O80: =XLOOKUP(D80,'Vendor Mapping'!$A:$A,'Vendor Mapping'!$C:$C,"Not Found") | P80: =IF(COUNTIFS($D:$D,D80,$B:$B,B80,$K:$K,K80)>1,"Duplicate","Unique") | Q80: =TEXT(B80,"mmm")
A81: INV-0080 | B81: 2025-09-17 | C81: 2025-11-01 | D81: V002 | E81: Tech Solutions Ltd | F81: Software | G81: IT | H81: Cloud storage | I81: 4 | J81: 3195.31 | K81: 12781.24 | L81: Paid | M81: 2025-10-17 | N81: Cheque | O81: =XLOOKUP(D81,'Vendor Mapping'!$A:$A,'Vendor Mapping'!$C:$C,"Not Found") | P81: =IF(COUNTIFS($D:$D,D81,$B:$B,B81,$K:$K,K81)>1,"Duplicate","Unique") | Q81: =TEXT(B81,"mmm")
A82: INV-0008-DUP | B82: 2025-12-10 | C82: 2026-01-09 | D82: V004 | E82: Bright Marketing Co | F82: Marketing | G82: Marketing | H82: Digital advertising | I82: 20 | J82: 516.62 | K82: 10332.33 | L82: Pending | O82: =XLOOKUP(D82,'Vendor Mapping'!$A:$A,'Vendor Mapping'!$C:$C,"Not Found") | P82: =IF(COUNTIFS($D:$D,D82,$B:$B,B82,$K:$K,K82)>1,"Duplicate","Unique") | Q82: =TEXT(B82,"mmm")
A83: INV-0024-DUP | B83: 2025-09-21 | C83: 2025-10-06 | D83: V002 | E83: Tech Solutions Ltd | F83: Software | G83: IT | H83: Business application | I83: 5 | J83: 1481.97 | K83: 7409.86 | L83: Paid | M83: 2025-10-24 | N83: Credit Card | O83: =XLOOKUP(D83,'Vendor Mapping'!$A:$A,'Vendor Mapping'!$C:$C,"Not Found") | P83: =IF(COUNTIFS($D:$D,D83,$B:$B,B83,$K:$K,K83)>1,"Duplicate","Unique") | Q83: =TEXT(B83,"mmm")
A84: INV-0052-DUP | B84: 2025-06-26 | C84: 2025-08-10 | D84: V007 | E84: SafeGuard Security | F84: Facilities | G84: Facilities | H84: Security service | I84: 4 | J84: 1671.7 | K84: 6686.81 | L84: Pending | O84: =XLOOKUP(D84,'Vendor Mapping'!$A:$A,'Vendor Mapping'!$C:$C,"Not Found") | P84: =IF(COUNTIFS($D:$D,D84,$B:$B,B84,$K:$K,K84)>1,"Duplicate","Unique") | Q84: =TEXT(B84,"mmm")

Sheet Analysis
A1: Metric | B1: Value | D1: Expense Category | E1: Total Expense | G1: Vendor | H1: Total Expense | J1: Payment Status | K1: Invoice Count | L1: Amount | N1: Month | O1: Expense
A2: Total Expenses | B2: 644365.57 | D2: Facilities | E2: 161792.97 | G2: Bright Marketing Co | H2: 105967.49 | J2: Paid | K2: 52 | L2: 396411.13 | N2: Jan | O2: 73567.52
A3: Total Invoices | B3: 83 | D3: Software | E3: 123547.51 | G3: CleanPro Services | H3: 93065.03 | J3: Pending | K3: 22 | L3: 176934.52 | N3: Feb | O3: 78904.35
A4: Paid Amount | B4: 396411.13 | D4: Marketing | E4: 105967.49 | G4: Prime Travel Services | H4: 77275.69 | J4: Overdue | K4: 9 | L4: 71019.92 | N4: Mar | O4: 27985.62
A5: Pending Amount | B5: 176934.52 | D5: Office Supplies | E5: 97504.9 | G5: Tech Solutions Ltd | H5: 73046.67 | N5: Apr | O5: 46768.99
A6: Overdue Amount | B6: 71019.92 | D6: Travel | E6: 77275.69 | G6: SafeGuard Security | H6: 68727.94 | N6: May | O6: 43716.71
A7: Duplicate Invoice Records | B7: 3 | D7: Logistics | E7: 60766.47 | G7: ABC Office Supplies | H7: 66986.94 | N7: Jun | O7: 53668.66
D8: HR Services | E8: 17510.54 | G8: Metro Logistics | H8: 60766.47 | N8: Jul | O8: 41344.55
G9: CloudWorks Software | H9: 50500.84 | N9: Aug | O9: 49734.49
G10: FreshBite Catering | H10: 30517.96 | N10: Sep | O10: 65379.01
G11: PeopleFirst HR Services | H11: 17510.54 | N11: Oct | O11: 65646.05
N12: Nov | O12: 35485.76
N13: Dec | O13: 62163.86

Sheet Dashboard
A1: INVOICE & EXPENSE ANALYSIS DASHBOARD
A2: Microsoft Excel | 2025 Invoice & Expense Analysis
A4: Total Expenses | D4: Total Invoices | G4: Paid Amount | J4: Pending Amount | M4: Overdue Amount
A5: 644365.57 | D5: 83 | G5: 396411.13 | J5: 176934.52 | M5: 71019.92

Sheet Insights
A1: Business Insights
A2: 1. Highest-spend category: Facilities (161,792.97).
A3: 2. Highest-spend vendor: Bright Marketing Co (105,967.49).
A4: 3. Paid invoices account for 396,411.13; pending and overdue amounts should be prioritized.
A5: 4. Duplicate-check logic is included in Cleaned Data to flag repeated invoice combinations.
